{
  "kind": "collectionType",
  "collectionName": "doctors",
  "info": {
    "singularName": "doctor",
    "pluralName": "doctors",
    "displayName": "Doctor"
  },
  "options": {
    "draftAndPublish": false
  },
  "pluginOptions": {},
  "attributes": {
    "UUID": {
      "type": "customField",
      "customField": "plugin::strapi-advanced-uuid.uuid",
      "options": {
        "uuid-format": "^[0-9a-f]{8}-[0-9a-f]{4}-[0-9a-f]{4}-[0-9a-f]{4}-[0-9a-f]{12}$"
      }
    },
    "lastname": {
      "type": "string"
    },
    "firstname": {
      "type": "string"
    },
    "appointmentPhone": {
      "type": "string"
    }
  }
}
